strictdom-0.3.dist-info/zip-safe
strictdom-0.3.dist-info/WHEEL
strictdom-0.3.dist-info/METADATA
strictdom-0.3.dist-info/metadata.json
strictdom-0.3.dist-info/top_level.txt
strictdom-0.3.dist-info/DESCRIPTION.rst
strictdom-0.3.dist-info/RECORD
strictdom/__init__.py
strictdom/tags_1.py
