Metadata-Version: 2.0
Name: strictdom
Version: 0.3
Summary: strictly typed wrapper around Knio's Dominate
Home-page: https://github.com/tawesoft/strictdom
Author: Tawesoft Ltd
Author-email: opensource@tawesoft.co.uk
License: Creative Commons Attribution 4.0 International License and W3C Document License
Platform: UNKNOWN
Classifier: Development Status :: 4 - Beta
Classifier: Intended Audience :: Developers
Classifier: License :: Other/Proprietary License
Classifier: Programming Language :: Python :: 3
Classifier: Programming Language :: Python :: 3.4
Classifier: Topic :: Software Development :: Libraries :: Python Modules
Classifier: Topic :: Text Processing :: Markup :: HTML
Classifier: Topic :: Internet :: WWW/HTTP
